{
  "title": "Jameda Search Scraper",
  "description": "Search Jameda doctor profiles by specialty, doctor name, and optional German location.",
  "type": "object",
  "schemaVersion": 1,
  "anyOf": [
    {
      "required": [
        "searches"
      ]
    },
    {
      "required": [
        "q"
      ]
    }
  ],
  "properties": {
    "searches": {
      "title": "Searches",
      "type": "array",
      "description": "Recommended. Process many Jameda query/location searches in one Apify run so run startup and storage overhead are shared across doctor results.",
      "editor": "json",
      "prefill": [
        {
          "q": "Zahnarzt",
          "loc": "Berlin"
        },
        {
          "q": "Hausarzt",
          "loc": "München"
        }
      ],
      "items": {
        "type": "object",
        "required": ["q"],
        "properties": {
          "q": {
            "type": "string",
            "minLength": 2,
            "maxLength": 255
          },
          "loc": {
            "type": "string",
            "maxLength": 100
          }
        }
      }
    },
    "q": {
      "title": "Legacy Search Query",
      "type": "string",
      "description": "Backward-compatible single doctor name, specialty, symptom, or medical service to search on Jameda. Prefer searches for normal usage, especially when running more than one query.",
      "editor": "textfield",
      "minLength": 2,
      "maxLength": 255,
      "prefill": "Zahnarzt"
    },
    "loc": {
      "title": "Legacy Location",
      "type": "string",
      "description": "Optional German city or location for the legacy single query.",
      "editor": "textfield",
      "maxLength": 100,
      "prefill": "Berlin"
    },
    "page": {
      "title": "Start Page",
      "type": "integer",
      "description": "One-based Jameda search results page.",
      "editor": "number",
      "minimum": 1,
      "maximum": 500,
      "default": 1
    },
    "per_page": {
      "title": "Results Per Page",
      "type": "integer",
      "description": "Maximum doctor results to save per page. Jameda returns up to 28 results per page.",
      "editor": "number",
      "minimum": 1,
      "maximum": 28,
      "default": 28
    },
    "max_pages": {
      "title": "Maximum Pages",
      "type": "integer",
      "description": "Number of result pages to fetch, starting from Start Page.",
      "editor": "number",
      "minimum": 1,
      "maximum": 10,
      "default": 1
    }
  }
}
