{
  "actorSpecification": 1,
  "name": "youtube-api-search-data",
  "title": "YouTube Search Data Scraper",
  "description": "Search YouTube by query and filter results by type, sort order, duration, upload date, content type, features, limit, and continuation token.",
  "version": "0.0",
  "buildTag": "latest",
  "input": "./input_schema.json",
  "environmentVariables": { "SCRAPPA_API_KEY": "@SCRAPPA_API_KEY" },
  "storages": {
    "dataset": "./dataset_schema.json"
  },
  "dockerfile": "./Dockerfile"
}
